mdeditor/__init__.py
mdeditor/widgets.py
django_mdeditor_widget-1.1.2.dist-info/LICENSE
django_mdeditor_widget-1.1.2.dist-info/METADATA
django_mdeditor_widget-1.1.2.dist-info/WHEEL
django_mdeditor_widget-1.1.2.dist-info/top_level.txt
django_mdeditor_widget-1.1.2.dist-info/RECORD
