Metadata-Version: 2.1
Name: django-mdeditor-widget
Version: 1.1.2
Summary: Django widget to edit markdown in forms
Home-page: https://github.com/tschmoderer/django-mdeditor-widget
Author: Timothée Schmoderer
Author-email: timothee.schmoderer@netcourrier.com
License: UNKNOWN
Platform: UNKNOWN
Classifier: Environment :: Web Environment
Classifier: Framework :: Django
Classifier: Framework :: Django :: 3.0
Classifier: Intended Audience :: Developers
Classifier: Programming Language :: Python :: 3
Classifier: License :: OSI Approved :: GNU General Public License v3 or later (GPLv3+)
Classifier: Operating System :: OS Independent
Classifier: Topic :: Internet :: WWW/HTTP
Classifier: Topic :: Internet :: WWW/HTTP :: Dynamic Content
Requires-Python: >=3.6
